{"errors":[],"detail":[{"repositories":[{"name":"eucalyptus","url":"https://github.com/eucalyptus/eucalyptus","commits":[{"id":"9020a9cbba1d05807f364d0b4bd21bcdd6e784c4","displayId":"9020a9c","authorTimestamp":"2012-07-27T11:07:05.000+0000","url":"https://github.com/eucalyptus/eucalyptus/commit/9020a9cbba1d05807f364d0b4bd21bcdd6e784c4","author":{"name":"osenft","avatar":"https://avatars0.githubusercontent.com/u/2054123?v=4","url":"https://github.com/osenft"},"fileCount":3,"merge":false,"message":"Fixes EUCA-3012.\n- Makes the following Node Controller timeout settings configurable from eucalyptus.conf:\n  - NC_STAGING_CLEANUP_THRESHOLD\n  - NC_BOOTING_CLEANUP_THRESHOLD\n  - NC_BUNDLING_CLEANUP_THRESHOLD\n  - NC_CREATEIMAGE_CLEANUP_THRESHOLD\n  - NC_TEARDOWN_STATE_DURATION\n  If these settings are not provided the previous defaults are applied.\n- Increases the timeouts for NC_BUNDLING_CLEANUP_THRESHOLD and NC_CREATEIMAGE_CLEANUP_THRESHOLD from 1h to 2h.","files":[{"path":"node/handlers.c","url":"https://github.com/eucalyptus/eucalyptus/commit/9020a9cbba1d05807f364d0b4bd21bcdd6e784c4#diff-0","changeType":"MODIFIED","linesAdded":15,"linesRemoved":10},{"path":"node/handlers.h","url":"https://github.com/eucalyptus/eucalyptus/commit/9020a9cbba1d05807f364d0b4bd21bcdd6e784c4#diff-1","changeType":"MODIFIED","linesAdded":5,"linesRemoved":0},{"path":"util/eucalyptus.h","url":"https://github.com/eucalyptus/eucalyptus/commit/9020a9cbba1d05807f364d0b4bd21bcdd6e784c4#diff-2","changeType":"MODIFIED","linesAdded":5,"linesRemoved":0}]}]}],"_instance":{"singleInstance":true,"baseUrl":"https://github.com","name":"GitHub","typeName":"GitHub","id":"github","type":"github"}}]}